{
    "_links": {
        "self": {
            "href": "http:\/\/default\/user\/7?_format=hal_json"
        },
        "type": {
            "href": "http:\/\/drupal.org\/rest\/type\/user\/user"
        },
        "http:\/\/drupal.org\/rest\/relation\/user\/user\/user_picture": [
            {
                "href": "",
                "lang": "en"
            }
        ]
    },
    "uid": [
        {
            "value": 7
        }
    ],
    "uuid": [
        {
            "value": "3aa4f897-4b37-4e07-8608-41428afb2163"
        }
    ],
    "langcode": [
        {
            "value": "en",
            "lang": "en"
        }
    ],
    "preferred_langcode": [
        {
            "value": "en"
        }
    ],
    "preferred_admin_langcode": [
        {
            "value": "en"
        }
    ],
    "name": [
        {
            "value": "AshRydell"
        }
    ],
    "mail": [
        {
            "value": "ash@example.com"
        }
    ],
    "timezone": [
        {
            "value": "UTC"
        }
    ],
    "status": [
        {
            "value": true
        }
    ],
    "created": [
        {
            "value": "2019-08-29T23:51:10+00:00",
            "format": "Y-m-d\\TH:i:sP"
        }
    ],
    "changed": [
        {
            "value": "2020-03-16T15:39:39+00:00",
            "lang": "en",
            "format": "Y-m-d\\TH:i:sP"
        }
    ],
    "access": [
        {
            "value": "1970-01-01T00:00:00+00:00",
            "format": "Y-m-d\\TH:i:sP"
        }
    ],
    "login": [
        {
            "value": "1970-01-01T00:00:00+00:00",
            "format": "Y-m-d\\TH:i:sP"
        }
    ],
    "init": [
        {
            "value": "ash@example.com"
        }
    ],
    "roles": [
        {
            "target_id": "administrator"
        },
        {
            "target_id": "creator"
        },
        {
            "target_id": "reviewer"
        }
    ],
    "default_langcode": [
        {
            "value": true,
            "lang": "en"
        }
    ],
    "metatag": [
        {
            "value": {
                "title": "AshRydell | One",
                "canonical_url": "http:\/\/default\/user\/7",
                "description": "One"
            }
        }
    ],
    "path": [
        {
            "alias": null,
            "pid": null,
            "langcode": "en",
            "lang": "en"
        }
    ],
    "field_first_name": [
        {
            "value": "Ash",
            "lang": "en"
        }
    ],
    "field_last_name": [
        {
            "value": "Rydell",
            "lang": "en"
        }
    ],
    "_embedded": {
        "http:\/\/drupal.org\/rest\/relation\/user\/user\/user_picture": [
            {
                "_links": {
                    "self": {
                        "href": ""
                    },
                    "type": {
                        "href": "http:\/\/drupal.org\/rest\/type\/file\/file"
                    }
                },
                "uuid": [
                    {
                        "value": "5986b824-3b4b-43b6-a973-3684205f7fab"
                    }
                ],
                "lang": "en",
                "alt": "",
                "title": "",
                "width": "128",
                "height": "128"
            }
        ]
    }
}